pytheory/__init__.py
pytheory/_statics.py
pytheory/charts.py
pytheory/chords.py
pytheory/play.py
pytheory/scales.py
pytheory/systems.py
pytheory/tones.py
pytheory-0.2.0.dist-info/METADATA
pytheory-0.2.0.dist-info/WHEEL
pytheory-0.2.0.dist-info/top_level.txt
pytheory-0.2.0.dist-info/RECORD
