Metadata-Version: 2.1
Name: pytheory
Version: 0.2.0
Summary: Add your description here
Requires-Python: >=3.10
Requires-Dist: pytuning
Requires-Dist: numeral
Requires-Dist: sounddevice
Requires-Dist: scipy
